ossnake/__init__.py
ossnake/main.py
ossnake/settings.json
ossnake/assets/loading.gif
ossnake/assets/icons/back.png
ossnake/assets/icons/file.png
ossnake/assets/icons/folder.png
ossnake/docs/features.md
ossnake/driver/__init__.py
ossnake/driver/aws_s3.py
ossnake/driver/base_oss.py
ossnake/driver/callbacks.py
ossnake/driver/exceptions.py
ossnake/driver/minio_client.py
ossnake/driver/models.py
ossnake/driver/oss_ali.py
ossnake/driver/oss_config.py
ossnake/driver/transfer_manager.py
ossnake/driver/types.py
ossnake/ui/__init__.py
ossnake/ui/bucket_view.py
ossnake/ui/file_preview.py
ossnake/ui/main_window.py
ossnake/ui/progress_window.py
ossnake/ui/settings.py
ossnake/ui/components/__init__.py
ossnake/ui/components/bucket_list.py
ossnake/ui/components/loading_indicator.py
ossnake/ui/components/object_list.py
ossnake/ui/components/oss_source_dialog.py
ossnake/ui/components/progress_dialog.py
ossnake/ui/components/settings_dialog.py
ossnake/ui/components/toast.py
ossnake/ui/viewers/base_viewer.py
ossnake/ui/viewers/image_viewer.py
ossnake/ui/viewers/text_editor.py
ossnake/utils/__init__.py
ossnake/utils/clipboard_helper.py
ossnake/utils/config_manager.py
ossnake/utils/file_type_manager.py
ossnake/utils/helper_functions.py
ossnake/utils/proxy_manager.py
ossnake/utils/settings_manager.py
ossnake/utils/tkv_test.py
ossnake/utils/transfer_manager.py
ossnake/utils/vlc_test.py
ossnake-0.1.4.dist-info/METADATA
ossnake-0.1.4.dist-info/WHEEL
ossnake-0.1.4.dist-info/entry_points.txt
ossnake-0.1.4.dist-info/top_level.txt
ossnake-0.1.4.dist-info/RECORD
