Metadata-Version: 2.1
Name: ossnake
Version: 0.1.4
Summary: A unified object storage browser supporting multiple cloud storage services
Home-page: https://github.com/jimeverest/ossnake
Author: Jim Everest
Author-email: your.email@example.com
Classifier: Development Status :: 3 - Alpha
Classifier: Intended Audience :: Developers
Classifier: License :: OSI Approved :: MIT License
Classifier: Operating System :: OS Independent
Classifier: Programming Language :: Python :: 3
Classifier: Programming Language :: Python :: 3.8
Classifier: Programming Language :: Python :: 3.9
Classifier: Programming Language :: Python :: 3.10
Requires-Python: >=3.8
Requires-Dist: boto3 >=1.26.0
Requires-Dist: oss2 >=2.16.0
Requires-Dist: minio >=7.1.0
Requires-Dist: Pillow >=9.0.0
Requires-Dist: requests >=2.28.0
Requires-Dist: tkinterdnd2
